quack2tex/__init__.py
quack2tex/cli.py
quack2tex/pyqt.py
quack2tex/decors/__init__.py
quack2tex/decors/gui_exception.py
quack2tex/enums/__init__.py
quack2tex/enums/capture_mode.py
quack2tex/repository/__init__.py
quack2tex/repository/menu_item_repository.py
quack2tex/repository/models.py
quack2tex/repository/prompt_repository.py
quack2tex/repository/db/__init__.py
quack2tex/repository/db/async_session.py
quack2tex/repository/db/registry.py
quack2tex/repository/db/session_manager.py
quack2tex/repository/db/sync_session.py
quack2tex/resources/__init__.py
quack2tex/resources/resources.qrc
quack2tex/resources/resources_rc.py
quack2tex/resources/files/index.html
quack2tex/resources/fonts/Roboto/LICENSE.txt
quack2tex/resources/fonts/Roboto/Roboto-Black.ttf
quack2tex/resources/fonts/Roboto/Roboto-BlackItalic.ttf
quack2tex/resources/fonts/Roboto/Roboto-Bold.ttf
quack2tex/resources/fonts/Roboto/Roboto-BoldItalic.ttf
quack2tex/resources/fonts/Roboto/Roboto-Italic.ttf
quack2tex/resources/fonts/Roboto/Roboto-Light.ttf
quack2tex/resources/fonts/Roboto/Roboto-LightItalic.ttf
quack2tex/resources/fonts/Roboto/Roboto-Medium.ttf
quack2tex/resources/fonts/Roboto/Roboto-MediumItalic.ttf
quack2tex/resources/fonts/Roboto/Roboto-Regular.ttf
quack2tex/resources/fonts/Roboto/Roboto-Thin.ttf
quack2tex/resources/fonts/Roboto/Roboto-ThinItalic.ttf
quack2tex/resources/icons/add.png
quack2tex/resources/icons/ai.png
quack2tex/resources/icons/anthropic.png
quack2tex/resources/icons/broom.png
quack2tex/resources/icons/check-all.png
quack2tex/resources/icons/close.png
quack2tex/resources/icons/copy-clipboard.png
quack2tex/resources/icons/delete.png
quack2tex/resources/icons/edit.png
quack2tex/resources/icons/gears.png
quack2tex/resources/icons/gemini.png
quack2tex/resources/icons/google.png
quack2tex/resources/icons/groq.png
quack2tex/resources/icons/loading.gif
quack2tex/resources/icons/ollama.png
quack2tex/resources/icons/openai.png
quack2tex/resources/icons/refresh.png
quack2tex-1.0.9.dist-info/METADATA
quack2tex-1.0.9.dist-info/WHEEL
quack2tex-1.0.9.dist-info/entry_points.txt
quack2tex-1.0.9.dist-info/RECORD
