Metadata-Version: 2.4
Name: quack2tex
Version: 1.0.9
Summary: Add your description here
Requires-Python: >=3.10
Requires-Dist: aiosqlite>=0.20.0
Requires-Dist: bleach>=6.2.0
Requires-Dist: google-cloud-texttospeech>=2.26.0
Requires-Dist: google-generativeai>=0.8.3
Requires-Dist: markdown2>=2.5.3
Requires-Dist: markdown>=3.7
Requires-Dist: matplotlib>=3.9.2
Requires-Dist: modihub
Requires-Dist: mss>=9.0.2
Requires-Dist: ollama>=0.3.3
Requires-Dist: openai-whisper>=20240930
Requires-Dist: openai>=1.52.0
Requires-Dist: pillow>=11.0.0
Requires-Dist: pydantic-settings>=2.6.0
Requires-Dist: pydantic>=2.9.2
Requires-Dist: pydub>=0.25.1
Requires-Dist: pyqt6-webengine>=6.9.0
Requires-Dist: pyqt6>=6.9.0
Requires-Dist: pyqtgraph>=0.13.7
Requires-Dist: python-dotenv>=1.0.1
Requires-Dist: scipy>=1.14.1
Requires-Dist: sounddevice>=0.5.1
Requires-Dist: sqlalchemy>=2.0.36
Requires-Dist: tenacity>=9.0.0
Requires-Dist: typer>=0.12.5
Provides-Extra: dev
